d_search/__init__.py
d_search/actions.py
d_search/cleaner.py
d_search/data.py
d_search/searcher.py
d_search/utils.py
d_search-0.1.3.dist-info/WHEEL
d_search-0.1.3.dist-info/METADATA
d_search-0.1.3.dist-info/RECORD
