Metadata-Version: 2.1
Name: d-search
Version: 0.1.3
Summary: 网页数据处理工具
Author: wangmengdi
Author-email: 790990241@qq.com
Requires-Python: >=3.8,<4.0
Classifier: Programming Language :: Python :: 3
Classifier: Programming Language :: Python :: 3.8
Classifier: Programming Language :: Python :: 3.9
Classifier: Programming Language :: Python :: 3.10
Classifier: Programming Language :: Python :: 3.11
Requires-Dist: pydantic (>=1.9.1,<1.10.0)
Requires-Dist: selenium (==4.6.0)
Requires-Dist: webdriver-manager (==3.8.5)
